InvoiceGenerator/__init__.py
InvoiceGenerator/api.py
InvoiceGenerator/conf.py
InvoiceGenerator/generator.py
InvoiceGenerator/pdf.py
InvoiceGenerator/pohoda.py
InvoiceGenerator/fonts/DejaVuSans-Bold.ttf
InvoiceGenerator/fonts/DejaVuSans.ttf
InvoiceGenerator/fonts/DejaVuSerif-Bold.ttf
InvoiceGenerator/fonts/DejaVuSerif.ttf
InvoiceGenerator/locale/cs/LC_MESSAGES/messages.mo
InvoiceGenerator/locale/cs/LC_MESSAGES/messages.po
InvoiceGenerator/locale/pt_BR/LC_MESSAGES/messages.mo
InvoiceGenerator/locale/pt_BR/LC_MESSAGES/messages.po
InvoiceGenerator-1.2.0.dist-info/METADATA
InvoiceGenerator-1.2.0.dist-info/WHEEL
InvoiceGenerator-1.2.0.dist-info/top_level.txt
InvoiceGenerator-1.2.0.dist-info/RECORD
