Metadata-Version: 2.1
Name: InvoiceGenerator
Version: 1.2.0
Summary: Library to generate PDF invoice.
Home-page: https://github.com/creckx/InvoiceGenerator
Author: Adam Strauch
Author-email: cx@initd.cz
License: BSD
Keywords: invoice invoices generator
Classifier: Development Status :: 3 - Alpha
Classifier: Programming Language :: Python
Classifier: Programming Language :: Python :: 3.5
Classifier: Topic :: Utilities
Classifier: License :: OSI Approved :: BSD License
Requires-Dist: reportlab
Requires-Dist: pillow
Requires-Dist: qrplatba (>=0.3.3)
Requires-Dist: babel
Provides-Extra: dev
Requires-Dist: flake8 ; extra == 'dev'
Requires-Dist: flake8-blind-except ; extra == 'dev'
Requires-Dist: flake8-comprehensions ; extra == 'dev'
Requires-Dist: flake8-import-order ; extra == 'dev'
Requires-Dist: flake8-tidy-imports ; extra == 'dev'
Provides-Extra: docs
Requires-Dist: sphinx ; extra == 'docs'
